{"0H2": [["4daw", 2]], "0K8": [["7otb", 1.6]], "0KA": [["4dhv", 1.95]], "0OD": [["4gjs", 1.85]], "0TN": [["5jeu", 0.97], ["5jev", 0.99], ["4jd8", 1.16]], "0UE": [["6i96", 1.85]], "188": [["1xkw", 2]], "1CL": [["6ug0", 1.83]], "2J0": [["4mj9", 0.97]], "2MO": [["2xts", 1.33], ["1dms", 1.88], ["1e60", 2]], "3WB": [["4x1a", 0.89]], "402": [["6yf4", 1.77], ["6gm4", 1.97]], "498": [["3p3j", 1.6]], "4HE": [["5ilr", 1.87]], "4IR": [["6ess", 1.91]], "670": [["3p55", 2]], "68G": [["5hpz", 1.96]], "6CO": [["5iks", 1.87]], "6CQ": [["5ile", 1.77], ["5ilp", 1.88]], "6HE": [["2ekt", 1.1]], "6SG": [["5l6x", 2]], "6WO": [["1e18", 2]], "76R": [["5t2k", 1.8]], "7HE": [["2eku", 1.4], ["2z97", 1.8]], "7MT": [["6frn", 1.74]], "7OH": [["7vm1", 2]], "830": [["2zy1", 1.78]], "8P8": [["5n6y", 1.35]], "8TH": [["5bru", 1.6]], "9CO": [["6fry", 1.7]], "9QQ": [["5obp", 1.593]], "9UX": [["6a71", 1.6]], "9ZQ": [["5lfx", 1.56]], "AF3": [["5c2k", 1.42], ["1n6k", 1.55], ["2wzd", 1.56], ["2hf7", 1.6], ["4dl8", 1.698]], "ALF": [["6i03", 1.02], ["2wf7", 1.05], ["5ok2", 1.1], ["6hdj", 1.16], ["2i7d", 1.2]], "AMS": [["3ca2", 2]], "APW": [["2dej", 1.5]], "AUC": [["1e3u", 1.66]], "B12": [["5nsa", 1.273], ["3gaj", 1.38], ["3gai", 1.48], ["6wgs", 1.5], ["5yrv", 1.55]], "B15": [["2foq", 1.25]], "B1M": [["1y80", 1.7]], "B69": [["2zcr", 1.92]], "B8B": [["5ogn", 1.1]], "BAZ": [["1xuf", 1.9]], "BCB": [["2wjn", 1.86], ["3t6e", 1.92], ["2wjm", 1.95], ["3t6d", 1.95], ["2i5n", 1.96]], "BCL": [["7p0q", 1.73], ["2x21", 1.75], ["1rzh", 1.8], ["2j8c", 1.87], ["4bcl", 1.9]], "BE7": [["3m2y", 1.17], ["3kne", 1.35], ["3m04", 1.4], ["4uxm", 1.5], ["1zfq", 1.55]], "BEF": [["2wf8", 1.2], ["5eyn", 1.289], ["5ojz", 1.3], ["6h90", 1.31], ["2wf9", 1.4]], "BF2": [["4ukd", 2]], "BFD": [["1j97", 1.5], ["2heg", 1.5], ["4xq0", 1.85], ["3hzh", 1.96], ["1rlo", 2]], "BJ5": [["6enk", 1.96]], "BJ8": [["6eno", 1.635], ["7yzm", 1.82], ["7yzq", 1.96]], "BOZ": [["1xuj", 1.92]], "BVA": [["2p8o", 1.5]], "BVQ": [["4uqu", 1.595], ["5m90", 1.599], ["4ur1", 1.649], ["5m8z", 1.659], ["5m91", 1.719]], "BW9": [["6jmw", 1.85]], "C1O": [["1aoz", 1.9], ["3g5w", 1.9]], "C2C": [["1pf3", 1.5], ["1n68", 1.7]], "C2O": [["1kv7", 1.4], ["7f0v", 1.494], ["2yxw", 1.5], ["7f19", 1.773], ["6xiz", 1.8]], "C4R": [["2zur", 1.8]], "CBY": [["5m29", 1.5], ["5m3b", 1.5], ["5nrp", 1.569], ["5m34", 1.6], ["5m2q", 1.7]], "CFC": [["1a3l", 1.95]], "CFM": [["1qgu", 1.6], ["1qh1", 1.6], ["1qh8", 1.6], ["1h1l", 1.9]], "CFN": [["1m1n", 1.16]], "CFO": [["3agt", 1.4], ["1a7d", 1.8], ["3agu", 1.805], ["3whn", 1.9]], "CL7": [["2x1z", 1.8]], "CLA": [["6a2w", 1.8], ["5b66", 1.85], ["5b5e", 1.87], ["7rf1", 1.89], ["3wu2", 1.9]], "CLF": [["7jrf", 1.33], ["5n6y", 1.35], ["6o7m", 1.4], ["4tku", 1.43], ["4tkv", 1.5]], "CLN": [["1ymc", 2]], "CMH": [["2foq", 1.25]], "CN1": [["1r1n", 1.74]], "CNB": [["1r1n", 1.74]], "CNC": [["5np4", 1.434], ["7biz", 1.53], ["1ccw", 1.6], ["5ysc", 1.673], ["1uc4", 1.8]], "CNF": [["1r1n", 1.74]], "COB": [["5ujc", 1.35], ["4jgi", 1.5], ["7qbt", 1.9], ["3sc0", 1.95]], "COH": [["1lfm", 1.5], ["2zdp", 1.5], ["2o5s", 1.6], ["2o5t", 1.6], ["1yog", 1.65]], "CON": [["2i7s", 1.35]], "COY": [["1eex", 1.7], ["1egv", 1.75]], "CPO": [["1esz", 2]], "CPT": [["1a2e", 1.63], ["1i1p", 1.63], ["3txf", 1.69], ["3txg", 1.7], ["3lpv", 1.77]], "CQ4": [["4xxu", 1.43], ["7t50", 1.9]], "CU6": [["5l3y", 1.7], ["5wbc", 1.72]], "CUA": [["7coh", 1.3], ["7w3e", 1.45], ["5b1a", 1.5], ["7ypy", 1.5], ["6y72", 1.55]], "CUO": [["3wky", 1.801]], "CUP": [["2eb8", 1.65]], "CUS": [["2eb9", 1.8]], "CUZ": [["1fwx", 1.6]], "D6N": [["7adr", 1], ["7ady", 1.05], ["7aiz", 1.05], ["6fea", 1.2]], "DAA": [["1bs1", 1.8]], "DAE": [["1d1a", 2]], "DEF": [["1k2v", 1.97]], "DEU": [["1pyz", 1.25]], "DHE": [["1qks", 1.28], ["1gq1", 1.4], ["1hj5", 1.46], ["1e2r", 1.59], ["1dy7", 1.6]], "DOZ": [["2z9k", 1.85]], "DTZ": [["2ztx", 1.72], ["2zu2", 1.8], ["2z9j", 1.95]], "DVG": [["4zn5", 1.12]], "DW2": [["2bzi", 1.9]], "EJ2": [["6g7r", 1.2], ["6gal", 1.25], ["6fpw", 1.35], ["6fpi", 1.5]], "EMC": [["5lu8", 1.95]], "EQQ": [["6g8s", 1.66], ["6r6d", 1.838]], "F3S": [["4u9h", 0.89], ["6fpo", 1.05], ["4u9i", 1.06], ["1wuk", 1.1], ["5adu", 1.1]], "F43": [["5a0y", 1.1], ["1hbn", 1.16], ["1mro", 1.16], ["3pot", 1.2], ["5g0r", 1.25]], "F4S": [["3ayx", 1.18], ["5mdl", 1.41], ["3uqy", 1.47], ["5mdj", 1.48], ["3rgw", 1.5]], "FC6": [["1vzg", 1.69], ["1vzh", 1.69], ["1urv", 2]], "FCO": [["5jsk", 0.95], ["6z8m", 1.02], ["5jsy", 1.04], ["6fpo", 1.05], ["6z8j", 1.09]], "FDE": [["6vdr", 1.87], ["3hcp", 2]], "FE9": [["6hav", 1.06], ["6hae", 1.85], ["6huz", 1.85]], "FEA": [["2avk", 1.53], ["2hmz", 1.66]], "FEC": [["6sv3", 1.64000868883], ["7q4g", 1.82], ["6xuc", 1.8702]], "FEL": [["1f1x", 1.6]], "FEO": [["4a9v", 1.1], ["4alf", 1.25], ["2mhr", 1.3], ["5v8s", 1.41], ["1ute", 1.55]], "FES": [["6lk1", 0.9], ["3wcq", 0.97], ["4udx", 1.03], ["1m2d", 1.05], ["1n62", 1.09]], "FLL": [["3fxz", 1.64]], "FMI": [["1s73", 1.53], ["1sbm", 1.69], ["1sdq", 1.69]], "FNE": [["1ubk", 1.18], ["1ubl", 1.2], ["1ubr", 1.34], ["1ubt", 1.34], ["1ubh", 1.35]], "FS2": [["1w9m", 1.35]], "FSO": [["1gnl", 1.25], ["1e1d", 1.72], ["1e9v", 1.79]], "FSX": [["1e3d", 1.8]], "FV1": [["3qvf", 1.85]], "GAK": [["5auk", 1.62]], "GCR": [["1efd", 1.9]], "GIX": [["3qug", 1.7]], "GWQ": [["6hwg", 1.74]], "H57": [["4jfv", 1.88]], "HAS": [["3s8f", 1.8], ["3s8g", 1.8], ["4g7s", 2]], "HB1": [["2bzh", 1.9]], "HBF": [["5myq", 1.89]], "HC1": [["1feh", 1.8]], "HCN": [["3c8y", 1.39]], "HCO": [["1qyz", 1.4]], "HDD": [["6ztx", 1.3], ["4aum", 1.4], ["7vn0", 1.4], ["5xzm", 1.41], ["5xzn", 1.47]], "HE6": [["1iop", 1.9]], "HEA": [["5b1a", 1.5], ["1v54", 1.8], ["2dyr", 1.8], ["3ag3", 1.8], ["8ijn", 1.8]], "HEB": [["4j20", 1.3], ["4max", 1.444], ["6a6q", 1.67], ["4y7s", 2]], "HEC": [["2ykz", 0.84], ["3zqv", 0.84], ["4eic", 0.84], ["2yl7", 0.9], ["3ztm", 0.9]], "HEG": [["1qsh", 1.7], ["1qsi", 1.7]], "HEM": [["5yce", 0.77], ["3x32", 0.83], ["1x8p", 0.85], ["1gwe", 0.88], ["4o6u", 0.89]], "HF3": [["1o7t", 1.65]], "HF5": [["1o7t", 1.65]], "HFM": [["1r0q", 1.61]], "HGB": [["5byi", 1.15], ["5t74", 1.2], ["5t71", 1.3], ["5t72", 1.3], ["3ibu", 1.41]], "HIF": [["1kok", 1.7]], "HKL": [["3ba2", 1.8]], "HNI": [["6ka9", 1.4], ["6lcw", 1.4], ["6lcx", 1.4], ["1j40", 1.45], ["1j41", 1.45]], "HNN": [["5yl3", 1.5]], "HWS": [["6e4v", 2]], "ICE": [["7jrf", 1.33], ["4tkv", 1.5]], "ICG": [["5bvg", 1.6]], "ICS": [["3u7q", 1], ["4wes", 1.08], ["6o7m", 1.4], ["4tku", 1.43], ["6op3", 1.6]], "ICZ": [["6ug0", 1.83]], "IME": [["1jzi", 1.62], ["1jzj", 1.8]], "IRI": [["7eog", 1.5], ["1icg", 1.53], ["4xwf", 1.8], ["5kpy", 2]], "ISW": [["6m0q", 1.99]], "IUM": [["2olb", 1.4], ["1t9h", 1.6], ["1b58", 1.8]], "J7U": [["7emp", 1.5]], "J7X": [["7emu", 1.35], ["7emq", 1.5]], "J83": [["7emr", 1.55]], "JSD": [["4xxr", 1.18]], "JSE": [["5top", 1.18]], "KC1": [["6a2w", 1.8]], "KC2": [["6a2w", 1.8]], "KHN": [["6rso", 1.97]], "KM3": [["6vo9", 1.5], ["6vp3", 1.65], ["6vob", 1.7], ["7kby", 1.7], ["6vp2", 1.8]], "KQB": [["6s0j", 1.5], ["7oyf", 1.88]], "KYT": [["2wpu", 1.92]], "L2D": [["4dcx", 2]], "L2M": [["4dcy", 2]], "M10": [["6rke", 1.7]], "MAP": [["2dei", 1.7], ["7mxj", 1.92], ["7mxk", 1.99]], "MBO": [["4yxi", 0.96], ["4yx4", 1.01], ["4yxo", 1.06], ["4yyt", 1.07], ["4yxu", 1.08]], "MGF": [["6ydj", 1.04], ["4c4r", 1.1], ["6hdl", 1.16], ["2wf5", 1.3], ["6hdm", 1.3]], "MH0": [["3wah", 1.54], ["6vd3", 1.67], ["4l7y", 1.8], ["6vd4", 1.954]], "MH2": [["1ixb", 0.9], ["1zlz", 1.55]], "MI9": [["7wy2", 1.45], ["6jmh", 1.46], ["7w9d", 1.55], ["7wy1", 1.6], ["7wy3", 1.6]], "MM1": [["1yik", 1.75]], "MM2": [["1yil", 1.6]], "MM5": [["2h9j", 1.75]], "MM6": [["2h9k", 1.75]], "MNH": [["6jzs", 1.68], ["2o5q", 1.9], ["2ayl", 2], ["2o5b", 2]], "MNQ": [["1d0x", 2]], "MNR": [["2fe6", 1.5], ["6vdw", 1.5], ["2o5o", 1.6], ["2o58", 1.65], ["2o5m", 1.65]], "MO7": [["1p0z", 1.6]], "MOO": [["2r8u", 1.35], ["4bvp", 1.49], ["3psh", 1.5], ["3gzg", 1.55], ["2onr", 1.6]], "MOS": [["3ml1", 1.6], ["3nvw", 1.6], ["3nvz", 1.6], ["3unc", 1.65], ["3o5a", 1.72]], "MOW": [["3bdj", 2]], "MQP": [["7emw", 1.12], ["7emo", 1.5], ["7emt", 1.8], ["7ems", 1.85]], "MSS": [["5k3x", 1.6], ["2bpb", 1.9]], "MTV": [["2bii", 1.7]], "MYQ": [["2ato", 2]], "N7H": [["5ag1", 1.85]], "NCO": [["5v2h", 1.08001306231], ["1mf5", 1.1], ["2fij", 1.19], ["1d8x", 1.2], ["5d8t", 1.2]], "NFE": [["1h2r", 1.4], ["1h2a", 1.8]], "NFS": [["7xdm", 1.74], ["7xdn", 1.8], ["7xdp", 1.84]], "NFU": [["3rgw", 1.5], ["7odg", 1.62], ["5xle", 1.69], ["4omf", 1.71], ["7vxq", 1.77]], "NFV": [["7odh", 1.34], ["5mdl", 1.41], ["4iuc", 1.45], ["4iud", 1.45], ["5d51", 1.47]], "NOB": [["2yze", 1.99]], "NWN": [["4u9i", 1.06]], "NWS": [["6q32", 1.39]], "NXC": [["3ef3", 1.5], ["3esa", 2]], "O6T": [["6y25", 1.95], ["6y2m", 1.95]], "O7Q": [["6y34", 1.307], ["6y33", 1.49], ["6y3q", 1.95]], "OBL": [["5obi", 1.599], ["5maa", 1.686]], "OEX": [["5b66", 1.85], ["5b5e", 1.87], ["7rf1", 1.89], ["3wu2", 1.9], ["5v2c", 1.9]], "OFO": [["1a7e", 1.8]], "OL3": [["6aue", 1.36]], "OL4": [["6auo", 1.7]], "OLS": [["6auc", 1.46]], "OMO": [["1n60", 1.19], ["1p0z", 1.6]], "ONP": [["1d0y", 2]], "OSW": [["6yj3", 1.55]], "P3C": [["6zrw", 1.35]], "PC4": [["6zrw", 1.35]], "PCD": [["1vlb", 1.28], ["1rm6", 1.6], ["3fah", 1.72], ["3fc4", 1.79]], "PDV": [["3f9b", 1.42]], "PHF": [["1o7t", 1.65]], "PLL": [["3np0", 1.48], ["3noz", 1.52], ["5yha", 1.58], ["2zg8", 1.6], ["3af8", 1.66]], "PNI": [["1em0", 0.9]], "PNQ": [["1d0z", 2]], "POR": [["2cmm", 1.8]], "PT7": [["6e2b", 1.45]], "PTE": [["6x6u", 1.944]], "PTT": [["1b25", 1.85]], "QG4": [["6uiz", 1.85]], "QHL": [["5ls8", 1.78]], "QPT": [["3txi", 1.6], ["4dd7", 1.6], ["4dd9", 1.6], ["3txh", 1.69]], "R1C": [["3gsk", 1.6]], "R1Z": [["4e1u", 0.92], ["5lfs", 1.85]], "REO": [["3r26", 1.7], ["3axf", 2]], "REP": [["2i7s", 1.35], ["3ibo", 1.45], ["1jzi", 1.62]], "REQ": [["2i7o", 1.5], ["4k9j", 1.7], ["6mjs", 1.85], ["6mjt", 1.893]], "RHD": [["1id9", 1.6], ["1iha", 1.6], ["1idw", 1.8]], "RHM": [["454d", 1.2]], "RHX": [["2ef2", 1.8]], "RKL": [["4qio", 0.95], ["3qrn", 1.1], ["4ltg", 1.18], ["4r8j", 1.21], ["5et2", 1.39]], "RKM": [["4x18", 1.05]], "RKP": [["4jd8", 1.16], ["5lfw", 1.28], ["4e7y", 1.7]], "RMD": [["3wjc", 2]], "RML": [["4e8s", 1.24], ["4e95", 1.94]], "RTA": [["1jzh", 1.7]], "RTB": [["1jzg", 1.4], ["1jzf", 1.5]], "RTC": [["1i53", 1.8]], "RU7": [["1t3p", 1.6]], "RUI": [["3we8", 1.954]], "RUR": [["6k9s", 1.55], ["3m0b", 2]], "S18": [["5vkx", 1.37]], "S32": [["5vl8", 1.7]], "SF3": [["6g7r", 1.2], ["1oa0", 1.25], ["6gal", 1.25], ["6fpw", 1.35], ["5lry", 1.4]], "SF4": [["5d8v", 0.48], ["7vos", 0.66], ["3a38", 0.7], ["3a39", 0.72], ["1iua", 0.8]], "SFS": [["5fez", 1.35], ["5ff0", 1.49]], "SI4": [["5k67", 1.7]], "SI7": [["5wbd", 1.5]], "SI8": [["5wba", 1.5]], "SIR": [["2xwp", 1.9]], "SMO": [["1t3q", 1.8]], "SNF": [["4kxi", 2]], "SRM": [["3vkt", 1.3], ["3vlx", 1.35], ["3vkp", 1.4], ["3vks", 1.4], ["3vm1", 1.5]], "SVA": [["1b8j", 1.9]], "SVP": [["5cse", 1.792]], "SXC": [["3esd", 1.22]], "TIL": [["2z68", 1.58]], "TPT": [["3ro0", 1.5], ["1qnq", 1.65], ["3ro1", 1.9]], "USN": [["7b1s", 0.992], ["7b2c", 1.8]], "UVC": [["6rsa", 2]], "UW8": [["7nz5", 1.9], ["7nys", 2]], "UWE": [["7nys", 2]], "V4O": [["1uzi", 1.89]], "VA3": [["1h2f", 2]], "VEA": [["3moo", 1.71]], "VHR": [["8bj8", 1.01], ["8bj7", 1.04]], "VKZ": [["7onv", 1.04], ["7onm", 1.769]], "VN3": [["5z5a", 1.8], ["6hwr", 1.95]], "VN4": [["2rbk", 1], ["2rar", 1.52], ["3e81", 1.629], ["5dmp", 1.793], ["4hgp", 1.8]], "VO4": [["4zn5", 1.12], ["2gso", 1.3], ["6lvq", 1.38], ["3f9b", 1.42], ["1rff", 1.7]], "VOV": [["6xub", 1.78]], "VVO": [["8aj5", 1.31], ["6vwq", 1.5], ["5bk9", 1.51], ["6zak", 1.54], ["6alr", 1.55]], "WCC": [["3cf4", 2]], "WO4": [["3cij", 1.07], ["1atg", 1.2], ["4rxl", 1.52], ["1gug", 1.6], ["3f9a", 1.69]], "WO5": [["1v0r", 1.7]], "WO6": [["2rb5", 1.03], ["2rav", 1.07]], "WPC": [["3w8o", 1.85]], "WVP": [["5xkb", 1.9]], "WXP": [["7emv", 1.45]], "XCC": [["6yu9", 1.904]], "YOK": [["1wzd", 1.35]], "YOL": [["1wzf", 1.85]], "YOM": [["3w8m", 1.46], ["1wzg", 1.75]], "ZEM": [["1ml2", 1.65]], "ZN0": [["5u82", 1.851]], "ZNH": [["2bcn", 1.7], ["3ase", 1.75]], "ZRC": [["1xc1", 1.51]]}